system/__init__.py
system/system.py
systemInfo-0.2.dist-info/DESCRIPTION.rst
systemInfo-0.2.dist-info/METADATA
systemInfo-0.2.dist-info/RECORD
systemInfo-0.2.dist-info/WHEEL
systemInfo-0.2.dist-info/metadata.json
systemInfo-0.2.dist-info/top_level.txt
