Metadata-Version: 2.0
Name: systemInfo
Version: 0.2
Summary: Implementation of system information apis
Home-page: UNKNOWN
Author: sudarshan
Author-email: sudarshanadmuthe@gmail.com
License: GPLv3
Keywords: system configuration information
Platform: UNKNOWN
